MiropayPaymentSDK.py
miropay-payment-sdk/__init__.py
miropay-payment-sdk/auth.py
miropay-payment-sdk/client.py
miropay-payment-sdk/constant.py
miropay-payment-sdk/enum.py
miropay-payment-sdk/interface.py
miropay_payment_sdk-0.0.2.dist-info/licenses/LICENSE
miropay_payment_sdk-0.0.2.dist-info/METADATA
miropay_payment_sdk-0.0.2.dist-info/WHEEL
miropay_payment_sdk-0.0.2.dist-info/top_level.txt
miropay_payment_sdk-0.0.2.dist-info/RECORD
