Metadata-Version: 2.4
Name: miropay-payment-sdk
Version: 0.0.2
Summary: Python SDK for MiroPay
Requires-Python: >=3.0
License-File: LICENSE
Requires-Dist: httpx
Requires-Dist: typing
Requires-Dist: cryptography
Dynamic: license-file
